apav/__init__.py
apav/pyxutils.cp310-win_amd64.pyd
apav/qt.py
apav/analysis/__init__.py
apav/analysis/background.py
apav/analysis/base.py
apav/analysis/grid_transfer.cp310-win_amd64.pyd
apav/analysis/massspectrum.py
apav/analysis/models.py
apav/analysis/spatial.py
apav/core/__init__.py
apav/core/histogram.py
apav/core/isotopic.py
apav/core/multipleevent.py
apav/core/range.py
apav/core/roi.py
apav/icons/copy.svg
apav/icons/export.svg
apav/icons/saveas.svg
apav/pyx/grid_transfer.c
apav/pyx/grid_transfer.pyx
apav/pyx/utils.c
apav/pyx/utils.pyx
apav/qtwidgets/__init__.py
apav/qtwidgets/controls.py
apav/qtwidgets/massrangewidget.py
apav/tests/Si.RNG
apav/tests/Si.RRNG
apav/tests/Si.apt
apav/tests/Si.epos
apav/tests/Si.pos
apav/tests/__init__.py
apav/tests/conftest.py
apav/tests/run_tests.py
apav/tests/test_background.py
apav/tests/test_helpers.py
apav/tests/test_histogram.py
apav/tests/test_isotopic.py
apav/tests/test_massspectrum.py
apav/tests/test_multiplevent.py
apav/tests/test_plotting.py
apav/tests/test_range.py
apav/tests/test_roi.py
apav/tests/test_spatial.py
apav/tests/test_validate.py
apav/utils/__init__.py
apav/utils/constants.py
apav/utils/helpers.py
apav/utils/logging.py
apav/utils/validate.py
apav/utils/version.py
apav/visualization/__init__.py
apav/visualization/base.py
apav/visualization/plotting.py
APAV-1.4.0.dist-info/LICENSE
APAV-1.4.0.dist-info/METADATA
APAV-1.4.0.dist-info/WHEEL
APAV-1.4.0.dist-info/top_level.txt
APAV-1.4.0.dist-info/RECORD
