Metadata-Version: 2.1
Name: APAV
Version: 1.4.0
Summary: A Python library for Atom Probe Tomography analysis
Home-page: https://apav.readthedocs.io/en/latest/
License: GPLv2+
Project-URL: Documentation, https://apav.readthedocs.io/en/latest/
Project-URL: Source, https://gitlab.com/jesseds/apav
Project-URL: Releases, https://gitlab.com/jesseds/apav/-/releases
Keywords: atom probe,tomography,field evaporation,data analysis,materials science
Classifier: Programming Language :: Python :: 3
Classifier: License :: OSI Approved :: GNU General Public License v2 or later (GPLv2+)
Classifier: Operating System :: OS Independent
Classifier: Intended Audience :: Science/Research
Classifier: Topic :: Scientific/Engineering :: Chemistry
Classifier: Topic :: Scientific/Engineering :: Visualization
Requires-Python: >=3.7
Provides-Extra: dev
License-File: LICENSE
